pycatch/__init__.py
pycatch/catch.py
pycatch/exceptions.py
pycatch/handlers.py
pycatch/throws.py
pycatch-0.0.1.dist-info/LICENSE
pycatch-0.0.1.dist-info/METADATA
pycatch-0.0.1.dist-info/WHEEL
pycatch-0.0.1.dist-info/top_level.txt
pycatch-0.0.1.dist-info/RECORD
