Metadata-Version: 2.1
Name: pycatch
Version: 0.0.1
Summary: Java-like exception declarations for python methods
Author-email: Michał Satława <mi.satlawa@gmail.com>
Project-URL: Homepage, https://github.com/misatlawa/pycatch
Project-URL: Issues, https://github.com/misatlawa/pycatch/issues
Classifier: Programming Language :: Python :: 3
Classifier: License :: OSI Approved :: MIT License
Classifier: Operating System :: OS Independent
Requires-Python: >=3.8
License-File: LICENSE
